anyrepo/__init__.py
anyrepo/__main__.py
anyrepo/_basemodel.py
anyrepo/_cli/__init__.py
anyrepo/_cli/common.py
anyrepo/_cli/info.py
anyrepo/_cli/manifest.py
anyrepo/_cli/options.py
anyrepo/_url.py
anyrepo/_util.py
anyrepo/anyrepo.py
anyrepo/appconfig.py
anyrepo/clone.py
anyrepo/const.py
anyrepo/datamodel.py
anyrepo/exceptions.py
anyrepo/filters.py
anyrepo/git.py
anyrepo/iters.py
anyrepo/types.py
anyrepo/workspace.py
anyrepo/workspacefinder.py
anyrepo-0.5.0.dist-info/entry_points.txt
anyrepo-0.5.0.dist-info/WHEEL
anyrepo-0.5.0.dist-info/METADATA
anyrepo-0.5.0.dist-info/RECORD
