Metadata-Version: 2.1
Name: anyrepo
Version: 0.5.0
Summary: Multi Repository Management Tool
Author: c0fec0de
Author-email: c0fec0de@gmail.com
Requires-Python: >=3.7,<4.0
Classifier: Operating System :: OS Independent
Classifier: Programming Language :: Python :: 3
Classifier: Programming Language :: Python :: 3.7
Classifier: Programming Language :: Python :: 3.8
Classifier: Programming Language :: Python :: 3.9
Classifier: Programming Language :: Python :: 3.10
Classifier: Programming Language :: Python :: 3
Requires-Dist: appdirs (>=1.4.4,<2.0.0)
Requires-Dist: click (>=8.0.0,<9.0.0)
Requires-Dist: coloredlogs (>=15.0.1,<16.0.0)
Requires-Dist: pydantic (>=1.10.0,<2.0.0)
Requires-Dist: tomlkit (>=0.11.5,<1.0.0)
